paper_feeds/__init__.py
paper_feeds/__main__.py
paper_feeds/app.py
paper_feeds/config.py
paper_feeds/const.py
paper_feeds/db.py
paper_feeds/decorators.py
paper_feeds/exceptions.py
paper_feeds/logging.py
paper_feeds/main.py
paper_feeds/migrations/README
paper_feeds/migrations/alembic.ini
paper_feeds/migrations/env.py
paper_feeds/migrations/script.py.mako
paper_feeds/migrations/versions/202401032156-680a75a_initial_migration.py
paper_feeds/migrations/versions/202401072216-53341bd_add_homepage_url_to_journal.py
paper_feeds/models/__init__.py
paper_feeds/models/api.py
paper_feeds/models/journal.py
paper_feeds/models/paper.py
paper_feeds/models/rss.py
paper_feeds/repositories/__init__.py
paper_feeds/repositories/journal_repository.py
paper_feeds/services/__init__.py
paper_feeds/services/crossref.py
paper_feeds/services/db.py
paper_feeds/services/journal_service.py
paper_feeds/services/openalex.py
paper_feeds/services/rss.py
paper_feeds/static/css/footer.css
paper_feeds/static/css/header.css
paper_feeds/static/css/search.css
paper_feeds/static/css/style.css
paper_feeds/static/css/tables.css
paper_feeds/static/img/rings.svg
paper_feeds/static/img/rss.svg
paper_feeds/static/js/htmx.min.js
paper_feeds/static/js/index.js
paper_feeds/templates/includes/footer-js.html
paper_feeds/templates/includes/footer.html
paper_feeds/templates/includes/head.html
paper_feeds/templates/includes/header.html
paper_feeds/templates/includes/section-search.html
paper_feeds/templates/pages/index.html
paper_feeds/templates/pages/journal.html
paper_feeds/templates/partials/feed-list.html
paper_feeds/templates/partials/make-feed-button.html
paper_feeds/templates/partials/paper-item.html
paper_feeds/templates/partials/paper-list-preload.html
paper_feeds/templates/partials/paper-list.html
paper_feeds/templates/partials/rss-button.html
paper_feeds/templates/partials/test-button.html
paper_feeds/templates/shared/default.html
paper_feeds-0.0.5.dist-info/LICENSE
paper_feeds-0.0.5.dist-info/METADATA
paper_feeds-0.0.5.dist-info/WHEEL
paper_feeds-0.0.5.dist-info/entry_points.txt
paper_feeds-0.0.5.dist-info/RECORD
